{
    "@class": "com.kony.gen.viz.model.component.KVizLabel",
    "DNDConfig": null,
    "_height_": {
        "type": "ref",
        "value": "preferred"
    },
    "_left_": {
        "type": "string",
        "value": "0dp"
    },
    "_margin_": [
        1,
        1,
        1,
        1
    ],
    "_padding_": [
        10,
        0,
        10,
        0
    ],
    "_skin_": "s7fb2bd9091941f6ad37ffd3ff5d461c",
    "_text_": "We are committed to helping you and your company to properly meet your training needs",
    "_top_": {
        "type": "string",
        "value": "1%"
    },
    "_width_": {
        "type": "string",
        "value": "100%"
    },
    "_wrapping_": 2,
    "android": {
        "textStyle": {
            "letterSpacing": 0,
            "strikeThrough": false
        }
    },
    "canUpdateUI": true,
    "centerx": {
        "type": "string",
        "value": "50%"
    },
    "containerweight": 100,
    "contentalignment": 5,
    "id": "lblSub",
    "info": null,
    "ipad": {
        "psp": {
            "wrapping": 2
        }
    },
    "iphone": {
        "psp": {
            "wrapping": 2
        },
        "textStyle": {
            "baseline": 0
        }
    },
    "iscustomlayout": false,
    "isvisible": true,
    "kuid": "b3dd5e492e4b4f85b9ae015617288986",
    "maxnumberoflines": "",
    "name": "kony.ui.Label",
    "parent": "StartScreen",
    "pf": "StartScreen",
    "retaincontentalignment": false,
    "retainflexpositionproperties": false,
    "textstyle": {},
    "tooltip": "",
    "wType": "Label",
    "zindex": 1
}